{
    "D8:07:B6:C5:96:A1": {
        "name": "",
        "ip": "10.0.0.1",
        "mac": "D8:07:B6:C5:96:A1",
        "first_seen": 1649665529.951473,
        "last_seen": 1649666854.01123
    },
    "68:63:59:DA:EE:5A": {
        "name": "",
        "ip": "10.0.0.2",
        "mac": "68:63:59:DA:EE:5A",
        "first_seen": 1649665529.951482,
        "last_seen": 1649666854.011234
    },
    "FA:73:D3:20:E5:3E": {
        "name": "Hans-Marius",
        "ip": "10.0.0.3",
        "mac": "FA:73:D3:20:E5:3E",
        "first_seen": 1649665529.9514828,
        "last_seen": 1649666854.011235
    },
    "68:07:0A:3D:91:90": {
        "name": "",
        "ip": "10.0.0.7",
        "mac": "68:07:0A:3D:91:90",
        "first_seen": 1649665529.951485,
        "last_seen": 1649666854.0112371
    },
    "42:17:3D:FE:05:89": {
        "name": "Halvor",
        "ip": "10.0.0.11",
        "mac": "42:17:3D:FE:05:89",
        "first_seen": 1649665529.9514859,
        "last_seen": 1649666854.0112379
    },
    "F8:4D:89:65:A1:DA": {
        "name": "",
        "ip": "10.0.0.24",
        "mac": "F8:4D:89:65:A1:DA",
        "first_seen": 1649665529.951488,
        "last_seen": 1649666854.011241
    },
    "5C:6A:80:D6:72:FC": {
        "name": "",
        "ip": "10.0.0.138",
        "mac": "5C:6A:80:D6:72:FC",
        "first_seen": 1649665529.951489,
        "last_seen": 1649666854.011243
    },
    "8E:12:7C:DA:AB:F9": {
        "name": "",
        "ip": "10.0.0.21",
        "mac": "8E:12:7C:DA:AB:F9",
        "first_seen": 1649665962.120212,
        "last_seen": 1649666854.01124
    }
}